MANIFEST.in
README.md
setup.cfg
setup.py
tsaw/VERSION
tsaw/__init__.py
tsaw.egg-info/PKG-INFO
tsaw.egg-info/SOURCES.txt
tsaw.egg-info/dependency_links.txt
tsaw.egg-info/top_level.txt