Metadata-Version: 1.1
Name: tsaw
Version: 0.4.8
Summary: TSAW : Torrent Server API Wrapper.
Home-page: https://github.com/ylaizet/tsaw
Author: Yec'han Laizet
Author-email: y.laizet@bordeaux.unicancer.fr
License: GPL3
Download-URL: https://github.com/ylaizet/tsaw/archive/0.4.8.tar.gz
Keywords: api,sequencer,Torrent server
Platform: UNKNOWN
Classifier: Programming Language :: Python
Classifier: Development Status :: 4 - Beta
Classifier: License :: OSI Approved :: GNU General Public License v3 (GPLv3)
Classifier: Natural Language :: English
Classifier: Operating System :: OS Independent
Classifier: Programming Language :: Python :: 2.7
Classifier: Topic :: Scientific/Engineering :: Bio-Informatics
